pytamaro/__init__.py
pytamaro/checks.py
pytamaro/color.py
pytamaro/color_functions.py
pytamaro/color_names.py
pytamaro/debug.py
pytamaro/graphic.py
pytamaro/io.py
pytamaro/localization.py
pytamaro/operations.py
pytamaro/point.py
pytamaro/point_names.py
pytamaro/primitives.py
pytamaro/py.typed
pytamaro/utils.py
pytamaro/de/__init__.py
pytamaro/de/color.py
pytamaro/de/color_names.py
pytamaro/de/graphic.py
pytamaro/de/io.py
pytamaro/de/operations.py
pytamaro/de/point.py
pytamaro/de/point_names.py
pytamaro/de/primitives.py
pytamaro/fr/__init__.py
pytamaro/fr/color.py
pytamaro/fr/color_names.py
pytamaro/fr/graphic.py
pytamaro/fr/io.py
pytamaro/fr/operations.py
pytamaro/fr/point.py
pytamaro/fr/point_names.py
pytamaro/fr/primitives.py
pytamaro/it/__init__.py
pytamaro/it/color.py
pytamaro/it/color_names.py
pytamaro/it/graphic.py
pytamaro/it/io.py
pytamaro/it/operations.py
pytamaro/it/point.py
pytamaro/it/point_names.py
pytamaro/it/primitives.py
pytamaro-1.1.4.dist-info/METADATA
pytamaro-1.1.4.dist-info/WHEEL
pytamaro-1.1.4.dist-info/top_level.txt
pytamaro-1.1.4.dist-info/RECORD
