Metadata-Version: 2.4
Name: pytamaro
Version: 1.1.4
Summary: Educational library for Python to teach programming using graphics
Author-email: Luca Chiodini <luca@chiodini.org>
Requires-Python: >=3.10
Requires-Dist: pillow==11.2.1
Requires-Dist: skia-python>=132.0b11
